mst_nft_mint/__init__.py
mst_nft_mint/abi.py
mst_nft_mint/mint.py
mst_nft_mint/networks.py
mst_nft_mint-0.1.0.dist-info/METADATA
mst_nft_mint-0.1.0.dist-info/WHEEL
mst_nft_mint-0.1.0.dist-info/top_level.txt
mst_nft_mint-0.1.0.dist-info/RECORD
